venvui/__init__.py
venvui/app.py
venvui/views.py
venvui/frontend/asset-manifest.json
venvui/frontend/favicon.ico
venvui/frontend/index.html
venvui/frontend/manifest.json
venvui/frontend/service-worker.js
venvui/frontend/static/css/main.6d331fe7.css
venvui/frontend/static/css/main.6d331fe7.css.map
venvui/frontend/static/css/main.84f4ce1d.css
venvui/frontend/static/css/main.84f4ce1d.css.map
venvui/frontend/static/js/main.2ddb3de4.js
venvui/frontend/static/js/main.2ddb3de4.js.map
venvui/frontend/static/js/main.fa343146.js
venvui/frontend/static/js/main.fa343146.js.map
venvui/services/__init__.py
venvui/services/config.py
venvui/services/deploy.py
venvui/services/logview.py
venvui/services/package.py
venvui/services/project.py
venvui/services/systemd.py
venvui/templates/systemd-simple.j2
venvui/utils/__init__.py
venvui/utils/misc.py
venvui/utils/streamlog.py
venvui/utils/subproc.py
venvui-0.1a10.dist-info/DESCRIPTION.rst
venvui-0.1a10.dist-info/METADATA
venvui-0.1a10.dist-info/RECORD
venvui-0.1a10.dist-info/WHEEL
venvui-0.1a10.dist-info/entry_points.txt
venvui-0.1a10.dist-info/metadata.json
venvui-0.1a10.dist-info/top_level.txt
