Metadata-Version: 2.0
Name: venvui
Version: 0.1a10
Summary: An user interface to manage Python projects and virtual environments.
Home-page: https://github.com/hjalves/venvui
Author: Humberto Alves
Author-email: hjalves@live.com
License: MIT
Keywords: venvui
Platform: UNKNOWN
Classifier: Development Status :: 2 - Pre-Alpha
Classifier: Environment :: Console
Classifier: Intended Audience :: Developers
Classifier: Operating System :: POSIX :: Linux
Classifier: Programming Language :: Python :: 3
Classifier: Programming Language :: Python :: 3.6
Requires-Dist: aiohttp
Requires-Dist: aiohttp-cors
Requires-Dist: colorlog
Requires-Dist: toml
Requires-Dist: pkginfo
Requires-Dist: jinja2
